tokenizers_pegasus/__init__.py
tokenizers_pegasus/data_utils.py
tokenizers_pegasus/tokenizers_pegasus.py
tokenizers_pegasus-0.0.8.post1.dist-info/METADATA
tokenizers_pegasus-0.0.8.post1.dist-info/WHEEL
tokenizers_pegasus-0.0.8.post1.dist-info/licenses/LICENSE
tokenizers_pegasus-0.0.8.post1.dist-info/RECORD
