Metadata-Version: 2.3
Name: tokenizers_pegasus
Version: 0.0.8.post1
Summary: pegasus tokenizers 
Project-URL: Homepage, https://github.com/Qiliang/pegasus
Project-URL: Issues, https://github.com/Qiliang/pegasus/issues
Author-email: xiaoql <xiaoql@hollycrm.com>
Classifier: License :: OSI Approved :: MIT License
Classifier: Operating System :: OS Independent
Classifier: Programming Language :: Python :: 3
Requires-Python: >=3.7
Requires-Dist: jieba
Requires-Dist: numpy
Requires-Dist: rouge
Requires-Dist: six
